{	"friction_zones": [],	"key_items": [],	"blocks": [ {	"pos": {	"__type_tag__": 774610643,	"__value__": [ 71.400002, -7.600000 ]},	"size": {	"__type_tag__": 774610643,	"__value__": [ 1.900002, 0.300000 ]},	"kind": 0,	"back": false}, {	"pos": {	"__type_tag__": 774610643,	"__value__": [ 69.900002, -9.200000 ]},	"size": {	"__type_tag__": 774610643,	"__value__": [ 4.300003, 0.299999 ]},	"kind": 0,	"back": false}, {	"pos": {	"__type_tag__": 774610643,	"__value__": [ 71.099998, -7.600000 ]},	"size": {	"__type_tag__": 774610643,	"__value__": [ 0.300003, 1.900000 ]},	"kind": 0,	"back": false}, {	"pos": {	"__type_tag__": 774610643,	"__value__": [ 74.000000, -9.200000 ]},	"size": {	"__type_tag__": 774610643,	"__value__": [ 0.300003, 3.500000 ]},	"kind": 0,	"back": false}, {	"pos": {	"__type_tag__": 774610643,	"__value__": [ 71.099998, -5.700000 ]},	"size": {	"__type_tag__": 774610643,	"__value__": [ 3.200005, 0.300000 ]},	"kind": 0,	"back": false}, {	"pos": {	"__type_tag__": 774610643,	"__value__": [ 67.900002, -10.600000 ]},	"size": {	"__type_tag__": 774610643,	"__value__": [ 7.000000, 0.300000 ]},	"kind": 0,	"back": false}, {	"pos": {	"__type_tag__": 774610643,	"__value__": [ 69.599998, -9.200000 ]},	"size": {	"__type_tag__": 774610643,	"__value__": [ 0.300003, 5.900000 ]},	"kind": 0,	"back": false}, {	"pos": {	"__type_tag__": 774610643,	"__value__": [ 69.900002, -3.600000 ]},	"size": {	"__type_tag__": 774610643,	"__value__": [ 6.300003, 0.300000 ]},	"kind": 0,	"back": false}, {	"pos": {	"__type_tag__": 774610643,	"__value__": [ 75.800003, -10.600000 ]},	"size": {	"__type_tag__": 774610643,	"__value__": [ 0.400002, 7.000000 ]},	"kind": 0,	"back": false}, {	"pos": {	"__type_tag__": 774610643,	"__value__": [ 74.599998, -10.600000 ]},	"size": {	"__type_tag__": 774610643,	"__value__": [ 1.200005, 0.300000 ]},	"kind": 0,	"back": false}, {	"pos": {	"__type_tag__": 774610643,	"__value__": [ 64.400002, -12.500000 ]},	"size": {	"__type_tag__": 774610643,	"__value__": [ 13.400002, 0.300000 ]},	"kind": 0,	"back": false}, {	"pos": {	"__type_tag__": 774610643,	"__value__": [ 64.099998, -12.500000 ]},	"size": {	"__type_tag__": 774610643,	"__value__": [ 0.300003, 12.200000 ]},	"kind": 0,	"back": false}, {	"pos": {	"__type_tag__": 774610643,	"__value__": [ 67.599998, -10.600000 ]},	"size": {	"__type_tag__": 774610643,	"__value__": [ 0.300003, 8.900001 ]},	"kind": 0,	"back": false}, {	"pos": {	"__type_tag__": 774610643,	"__value__": [ 67.900002, -2.000000 ]},	"size": {	"__type_tag__": 774610643,	"__value__": [ 9.900002, 0.300000 ]},	"kind": 0,	"back": false}, {	"pos": {	"__type_tag__": 774610643,	"__value__": [ 77.700005, -12.500000 ]},	"size": {	"__type_tag__": 774610643,	"__value__": [ 0.299995, 10.800000 ]},	"kind": 0,	"back": false}, {	"pos": {	"__type_tag__": 774610643,	"__value__": [ 70.800003, 0.900000 ]},	"size": {	"__type_tag__": 774610643,	"__value__": [ 5.599998, 0.300000 ]},	"kind": 0,	"back": false} ],	"torches": [],	"kill_zones": [],	"prest_sources": [ {	"pos": {	"__type_tag__": 774610643,	"__value__": [ 73.700005, -8.700000 ]},	"prest": 0.500000}, {	"pos": {	"__type_tag__": 774610643,	"__value__": [ 75.500000, -10.000000 ]},	"prest": 1.000000}, {	"pos": {	"__type_tag__": 774610643,	"__value__": [ 75.900002, -2.900000 ]},	"prest": 0.500000}, {	"pos": {	"__type_tag__": 774610643,	"__value__": [ 64.800003, -11.800000 ]},	"prest": 1.000000} ],	"next_zones": [ {	"pos": {	"__type_tag__": 774610643,	"__value__": [ 70.800003, 1.100000 ]},	"size": {	"__type_tag__": 774610643,	"__value__": [ 0.400002, 2.100000 ]},	"next_level": "1-27.json"} ],	"dry_zones": [],	"dispensers": [],	"decor_sprites": [],	"markers": [],	"rocks": [],	"doors": [],	"auto_binding_zones": [],	"trigger_zones": [],	"moving_blocks": [],	"camera_fixed_points": [ {	"camera": [ 0.000000, 0.000000, 0.000000, 0.000000 ]}, {	"camera": [ 63.702080, -12.624157, 14.383835, 16.524042 ]} ],	"player": {	"pos": {	"__type_tag__": 774610643,	"__value__": [ 71.400002, -7.215481 ]},	"prest": 0.000000},	"ambient": {	"color": {	"__type_tag__": 774610772,	"__value__": [ 1.000000, 1.000000, 1.000000, 1.000000 ]},	"intensity": 1.000000},	"camera": [ 58.304096, -13.284784, 25.600000, 14.400000 ]}